<?xml version="1.0" encoding="UTF-8"?>
<Contract xmlns="http://crd.gov.pl/wzor/2023/06/29/12650/">
  <ContractHeader>
    <ContractNumber>001/2025</ContractNumber>
    <ContractType>UMOWA ZLECENIE</ContractType>
    <ConclusionDate>2025-01-15</ConclusionDate>
    <ConclusionPlace>Warszawa</ConclusionPlace>
    <EffectiveDate>2025-01-15</EffectiveDate>
    <TerminationDate>2025-03-31</TerminationDate>
  </ContractHeader>
  
  <ContractingParties>
    <FirstParty>
      <PartyType>Zleceniodawca</PartyType>
      <PartyName>Firma ABC Sp. z o.o.</PartyName>
      <TaxIdentification>5213017228</TaxIdentification>
      <Address>
        <Street>ul. Przykładowa 1</Street>
        <City>Warszawa</City>
        <PostalCode>00-123</PostalCode>
        <CountryCode>PL</CountryCode>
      </Address>
      <Representative>Jan Nowak - Prezes Zarządu</Representative>
    </FirstParty>
    
    <SecondParty>
      <PartyType>Wykonawca</PartyType>
      <PartyName>Jan Kowalski</PartyName>
      <PersonalIdentification>12345678901</PersonalIdentification>
      <Address>
        <Street>ul. Robotnicza 15</Street>
        <City>Radom</City>
        <PostalCode>12-345</PostalCode>
        <CountryCode>PL</CountryCode>
      </Address>
      <Representative>Jan Kowalski</Representative>
    </SecondParty>
  </ContractingParties>
  
  <ContractSubject>
    <Description>Wykonanie usług programistycznych zgodnie z załącznikiem nr 1 do niniejszej umowy</Description>
    <ScopeOfWork>
      <Task>
        <TaskNumber>1</TaskNumber>
        <TaskDescription>Projektowanie i implementacja aplikacji webowej</TaskDescription>
        <TaskDeadline>2025-03-15</TaskDeadline>
      </Task>
      <Task>
        <TaskNumber>2</TaskNumber>
        <TaskDescription>Testowanie i wdrożenie systemu</TaskDescription>
        <TaskDeadline>2025-03-31</TaskDeadline>
      </Task>
    </ScopeOfWork>
  </ContractSubject>
  
  <FinancialTerms>
    <Remuneration>
      <Amount>5000.00</Amount>
      <Currency>PLN</Currency>
      <PaymentType>brutto</PaymentType>
      <PaymentSchedule>
        <Installment>
          <InstallmentNumber>1</InstallmentNumber>
          <Amount>2500.00</Amount>
          <DueDate>2025-02-28</DueDate>
          <Condition>Zakończenie etapu 1</Condition>
        </Installment>
        <Installment>
          <InstallmentNumber>2</InstallmentNumber>
          <Amount>2500.00</Amount>
          <DueDate>2025-04-15</DueDate>
          <Condition>Zakończenie etapu 2</Condition>
        </Installment>
      </PaymentSchedule>
    </Remuneration>
    
    <PaymentMethod>
      <Method>przelew</Method>
      <BankAccount>PL 98 7654 3210 9876 5432 1098 7654</BankAccount>
      <PaymentTerms>w terminie 7 dni od odbioru prac</PaymentTerms>
    </PaymentMethod>
  </FinancialTerms>
  
  <ContractTerms>
    <ConfidentialityClause>true</ConfidentialityClause>
    <IntellectualPropertyClause>true</IntellectualPropertyClause>
    <TerminationClause>
      <TerminationNotice>14 dni</TerminationNotice>
      <TerminationConditions>W przypadku niewykonania zobowiązań</TerminationConditions>
    </TerminationClause>
  </ContractTerms>
  
  <AdditionalProvisions>
    <Provision>
      <ProvisionNumber>1</ProvisionNumber>
      <ProvisionContent>Zmiany w umowie wymagają formy pisemnej pod rygorem nieważności</ProvisionContent>
    </Provision>
    <Provision>
      <ProvisionNumber>2</ProvisionNumber>
      <ProvisionContent>Wszelkie spory będą rozstrzygane przez sąd właściwy dla siedziby Zleceniodawcy</ProvisionContent>
    </Provision>
  </AdditionalProvisions>
  
  <ContractSignatures>
    <FirstPartySignature>
      <SignatureDate>2025-01-15</SignatureDate>
      <SignaturePlace>Warszawa</SignaturePlace>
      <AuthorizedPerson>Jan Nowak</AuthorizedPerson>
      <Position>Prezes Zarządu</Position>
    </FirstPartySignature>
    
    <SecondPartySignature>
      <SignatureDate>2025-01-15</SignatureDate>
      <SignaturePlace>Warszawa</SignaturePlace>
      <AuthorizedPerson>Jan Kowalski</AuthorizedPerson>
      <Position>Wykonawca</Position>
    </SecondPartySignature>
  </ContractSignatures>
  
  <Attachments>
    <Attachment>
      <AttachmentNumber>1</AttachmentNumber>
      <AttachmentName>Szczegółowy zakres prac</AttachmentName>
      <AttachmentPages>5</AttachmentPages>
    </Attachment>
  </Attachments>
</Contract>
